datadispatch/__init__.py
datadispatch/test/__init__.py
datadispatch/test/test_datadispatch.py
datadispatch-1.0.0.dist-info/METADATA
datadispatch-1.0.0.dist-info/WHEEL
datadispatch-1.0.0.dist-info/top_level.txt
datadispatch-1.0.0.dist-info/RECORD
