Metadata-Version: 2.1
Name: datadispatch
Version: 1.0.0
Summary: Like functools.singledispatch but for values
Home-page: https://github.com/pb-/datadispatch
Author: Paul Baecher
License: UNKNOWN
Platform: UNKNOWN
Classifier: Programming Language :: Python :: 3
Classifier: License :: OSI Approved :: MIT License
Classifier: Operating System :: OS Independent
